Metadata-Version: 2.1
Name: pydownloads
Version: 0.1.2
Summary: Statistics download python packages PiPy.
Home-page: https://github.com/pystorage/pydownloads
Author: PyMaster
Author-email: 
License: MIT
Keywords: statistics download python PiPy
Platform: UNKNOWN
Classifier: Programming Language :: Python
Classifier: Programming Language :: Python :: 3
Classifier: Programming Language :: Python :: 3.5
Classifier: Programming Language :: Python :: 3.6
Classifier: Programming Language :: Python :: 3.7
Classifier: Programming Language :: Python :: 3.8
Classifier: Topic :: Internet
Classifier: Topic :: Software Development :: Libraries
Classifier: Topic :: Software Development :: Libraries :: Python Modules
